hardware/verilog/d-flop-rtl/dflop3.v
//
// D-type flip-flop from Wiki page.
// Note 3-input gate with output M.
//
`timescale 1ns / 1ns

module main;

    //
    // Signals.
    //
    reg     cp;         // Clock input
    reg     d;          // Data input

    wire    q;          // Flop output
    wire    nq;         // Negated flop output
    wire    k, l, m, n; // Four intermediate NOR outputs

    //
    // Clock generator.
    //
    initial begin
        cp <= 0;

        #10; cp <= 1; #10; cp <= 0;
        #10; cp <= 1; #10; cp <= 0;
        #10; cp <= 1; #10; cp <= 0;
        #10; cp <= 1; #10; cp <= 0;
        #10; cp <= 1; #10; cp <= 0;
        #10; cp <= 1; #10; cp <= 0;

        #40; cp <= 1; #40; cp <= 0;
    end

    //
    // Six NOR gates.
    //
    assign #1 k = ~(l | n);
    assign #1 l = ~(k | cp);
    assign #1 m = ~(l | cp | n); // Note: three inputs
    assign #1 n = ~(m | d);
    assign #1 q = ~(l | nq);
    assign #1 nq = ~(m | q);

    initial begin
        $dumpfile("dflop3.vcd");
        $dumpvars(0, main);

        d <= 0;
        #45;
        d <= 1;
        $display ("(%0d) Asserting Data", $time);

        #40;
        d <= 0;
        $display ("(%0d) De-Asserting Data", $time);

        #40; d <= 1; #10; d <= 0;
        #10; d <= 1; #10; d <= 0;
        #10; d <= 1; #10; d <= 0;
        #10; d <= 1; #10; d <= 0;

        #20;
        $display ("(%0d) Terminating simulation", $time);
        $finish;
    end
endmodule

hardware/verilog/d-flop-rtl/dflop3.vcd
$date
	Fri Aug 12 23:24:05 2022
$end
$version
	Icarus Verilog
$end
$timescale
	1ns
$end
$scope module main $end
$var wire 1 ! k $end
$var wire 1 " l $end
$var wire 1 # m $end
$var wire 1 $ n $end
$var wire 1 % nq $end
$var wire 1 & q $end
$var reg 1 ' cp $end
$var reg 1 ( d $end
$upscope $end
$enddefinitions $end
#0
$dumpvars
0(
0'
x&
x%
x$
x#
x"
x!
$end
#10
1'
#11
0#
0"
#12
1$
#13
0!
#20
0'
#21
1"
#22
0&
#23
1%
#30
1'
#31
0"
#40
0'
#41
1"
#45
1(
#46
0$
#50
1'
#51
0"
#52
1!
#60
0'
#61
1#
#62
0%
#63
1&
#70
1'
#71
0#
#80
0'
#81
1#
#85
0(
#90
1'
#91
0#
#92
1$
#93
0!
#100
0'
#101
1"
#102
0&
#103
1%
#110
1'
#111
0"
#120
0'
#121
1"
#125
1(
#126
0$
#135
0(
#136
1$
#145
1(
#146
0$
#155
0(
#156
1$
#160
1'
#161
0"
#165
1(
#166
0$
#167
1!
#175
0(
#176
1$
#177
0!
#185
1(
#186
0$
#187
1!
#195
0(
#196
1$
#197
0!
#200
0'
#201
1"
